CHANGELOG.txt
LICENSE.txt
MANIFEST.in
README.txt
setup.py
Dataselector/__init__.py
Dataselector.egg-info/PKG-INFO
Dataselector.egg-info/SOURCES.txt
Dataselector.egg-info/dependency_links.txt
Dataselector.egg-info/requires.txt
Dataselector.egg-info/top_level.txt