Metadata-Version: 2.1
Name: Dataselector
Version: 0.0.4
Summary: A handy library to import dataset from various excel file types and URls
Home-page: 
Author: Siddharth Mishra
Author-email: Siddharth.mishra@ganitinc.co.in
License: MIT
Keywords: Dataset
Classifier: Development Status :: 5 - Production/Stable
Classifier: Intended Audience :: Education
Classifier: Operating System :: Microsoft :: Windows :: Windows 11
Classifier: License :: OSI Approved :: MIT License
Classifier: Programming Language :: Python :: 3
License-File: LICENSE.txt
